odoo9_addon_web_easy_switch_company-9.0.1.0.0.99.dev8-py2.7-nspkg.pth
odoo9_addon_web_easy_switch_company-9.0.1.0.0.99.dev8.dist-info/DESCRIPTION.rst
odoo9_addon_web_easy_switch_company-9.0.1.0.0.99.dev8.dist-info/METADATA
odoo9_addon_web_easy_switch_company-9.0.1.0.0.99.dev8.dist-info/RECORD
odoo9_addon_web_easy_switch_company-9.0.1.0.0.99.dev8.dist-info/WHEEL
odoo9_addon_web_easy_switch_company-9.0.1.0.0.99.dev8.dist-info/metadata.json
odoo9_addon_web_easy_switch_company-9.0.1.0.0.99.dev8.dist-info/namespace_packages.txt
odoo9_addon_web_easy_switch_company-9.0.1.0.0.99.dev8.dist-info/top_level.txt
odoo_addons/web_easy_switch_company/README.rst
odoo_addons/web_easy_switch_company/__init__.py
odoo_addons/web_easy_switch_company/__openerp__.py
odoo_addons/web_easy_switch_company/controllers/__init__.py
odoo_addons/web_easy_switch_company/controllers/main.py
odoo_addons/web_easy_switch_company/i18n/ca.po
odoo_addons/web_easy_switch_company/i18n/de.po
odoo_addons/web_easy_switch_company/i18n/es.po
odoo_addons/web_easy_switch_company/i18n/fr.po
odoo_addons/web_easy_switch_company/i18n/pt_BR.po
odoo_addons/web_easy_switch_company/model/__init__.py
odoo_addons/web_easy_switch_company/model/res_company.py
odoo_addons/web_easy_switch_company/model/res_users.py
odoo_addons/web_easy_switch_company/static/description/icon.png
odoo_addons/web_easy_switch_company/static/description/selection-off.png
odoo_addons/web_easy_switch_company/static/description/selection-on.png
odoo_addons/web_easy_switch_company/static/src/js/switch_company.js
odoo_addons/web_easy_switch_company/static/src/xml/switch_company.xml
odoo_addons/web_easy_switch_company/view/res_users_view.xml
